yodoit/__init__.py
yodoit/cli.py
yodoit/trello_api.py
yodoit/yodoit_config.py
yodoit-1.1.2.data/scripts/yodoit
yodoit-1.1.2.dist-info/DESCRIPTION.rst
yodoit-1.1.2.dist-info/METADATA
yodoit-1.1.2.dist-info/metadata.json
yodoit-1.1.2.dist-info/pbr.json
yodoit-1.1.2.dist-info/RECORD
yodoit-1.1.2.dist-info/top_level.txt
yodoit-1.1.2.dist-info/WHEEL
