Metadata-Version: 2.0
Name: yodoit
Version: 1.1.2
Summary: Python CLI for using an Eisenhower Decision Matrix with Trello
Home-page: https://github.com/niketanpatel/yodoit-cli
Author: Niketan Patel
Author-email: UNKNOWN
License: MIT
Keywords: todo list todolist trello developer cli eisenhower decision matrix box productivity method
Platform: UNKNOWN
